pyaudioai/OpenAiResponse.py
pyaudioai/RecordQuestion.py
pyaudioai/__init__.py
pyaudioai-0.0.2.dist-info/LICENSE
pyaudioai-0.0.2.dist-info/METADATA
pyaudioai-0.0.2.dist-info/WHEEL
pyaudioai-0.0.2.dist-info/top_level.txt
pyaudioai-0.0.2.dist-info/RECORD
