Metadata-Version: 2.1
Name: pyaudioai
Version: 0.0.2
Summary: Get an audio response from ChatGPT
Home-page: https://github.com/eberlemanuel/pyaudioai
Author: Manuel Eberle
Author-email: info@manueleberle.de
Project-URL: Documentation, https://github.com/eberlemanuel/pyaudioai
Project-URL: Bug Reports, https://github.com/eberlemanuel/pyaudioai/issues
Project-URL: Source Code, https://github.com/eberlemanuel/pyaudioai
Project-URL: Source Code Documenetation, https://eberlemanuel.github.io/pyaudioai
Keywords: chatgpt,openai,audio,tts,pypi,package
Classifier: Development Status :: 5 - Production/Stable
Classifier: Intended Audience :: Developers
Classifier: Topic :: Software Development :: Build Tools
Classifier: Programming Language :: Python :: 3
Classifier: Programming Language :: Python :: 3.8
Classifier: Programming Language :: Python :: 3.9
Classifier: Programming Language :: Python :: 3.10
Classifier: Programming Language :: Python :: 3.11
Classifier: Programming Language :: Python :: 3 :: Only
Classifier: License :: OSI Approved :: MIT License
Classifier: Operating System :: OS Independent
Requires-Python: >=3.8
License-File: LICENSE
Requires-Dist: openai
Requires-Dist: gTTS
Requires-Dist: playsound
Requires-Dist: pyaudio
Requires-Dist: wave
Provides-Extra: dev
Requires-Dist: check-manifest ; extra == 'dev'
Provides-Extra: test
Requires-Dist: coverage ; extra == 'test'
